botdata/__init__.py
botdata/_version.py
botdata/holiday.py
botdata-0.1.2.dist-info/LICENSE.txt
botdata-0.1.2.dist-info/METADATA
botdata-0.1.2.dist-info/WHEEL
botdata-0.1.2.dist-info/top_level.txt
botdata-0.1.2.dist-info/RECORD
