Metadata-Version: 2.1
Name: botdata
Version: 0.1.2
Summary: BOT Data is a Python package for retrieving data from the website of the Bank of Thailand
Home-page: https://github.com/ezyquant/BOT-Data
Author: Fintech (Thailand) Company Limited
Author-email: admin@fintech.co.th
Maintainer: Fintech (Thailand) Company Limited
Maintainer-email: admin@fintech.co.th
License: The MIT License (MIT)
Project-URL: Documentation, https://github.com/ezyquant/BOT-Data
Project-URL: Bug Reports, https://github.com/ezyquant/BOT-Data/issues
Project-URL: Source, https://github.com/ezyquant/BOT-Data
Classifier: Intended Audience :: Financial and Insurance Industry
Classifier: Programming Language :: Python :: 3
Classifier: License :: OSI Approved :: MIT License
Requires-Python: >=3.8
License-File: LICENSE.txt
Requires-Dist: pandas (>=1.2)
Requires-Dist: requests (>=2.0)
